muuntaa/__init__.py
muuntaa/__main__.py
muuntaa/api.py
muuntaa/cli.py
muuntaa/config.py
muuntaa/csaf.py
muuntaa/cvrf.py
muuntaa/report.py
muuntaa-2023.10.21.dist-info/LICENSE
muuntaa-2023.10.21.dist-info/METADATA
muuntaa-2023.10.21.dist-info/WHEEL
muuntaa-2023.10.21.dist-info/entry_points.txt
muuntaa-2023.10.21.dist-info/top_level.txt
muuntaa-2023.10.21.dist-info/RECORD
