Metadata-Version: 2.1
Name: muuntaa
Version: 2023.10.21
Summary: Convert (Finnish: muuntaa) CVRF v1.2 XML to CSAF v2.0 JSON documents.
Author-email: Stefan Hagen <stefan@hagen.link>
Maintainer-email: Stefan Hagen <stefan@hagen.link>
Project-URL: Homepage, https://git.sr.ht/~sthagen/muuntaa
Project-URL: Bug-Tracker, https://todo.sr.ht/~sthagen/muuntaa
Project-URL: Documentation, https://codes.dilettant.life/docs/muuntaa
Project-URL: Source-Code, https://git.sr.ht/~sthagen/muuntaa
Project-URL: Test-Coverage, https://codes.dilettant.life/coverage/muuntaa
Keywords: developer-tools,devops
Classifier: Development Status :: 3 - Alpha
Classifier: Intended Audience :: Developers
Classifier: License :: OSI Approved :: MIT License
Classifier: Programming Language :: Python :: 3.10
Classifier: Programming Language :: Python :: 3.11
Classifier: Programming Language :: Python :: 3.9
Requires-Python: >=3.9
License-File: LICENSE
Requires-Dist: msgspec >=0.18.4
Provides-Extra: dev
Requires-Dist: black ; extra == 'dev'
Requires-Dist: coverage ; extra == 'dev'
Requires-Dist: hypothesis ; extra == 'dev'
Requires-Dist: mypy ; extra == 'dev'
Requires-Dist: pytest ; extra == 'dev'
Requires-Dist: pytest-cov ; extra == 'dev'
Requires-Dist: pytest-flake8 ; extra == 'dev'
Requires-Dist: ruff ; extra == 'dev'
